brule/__init__.py
brule/_brule.py
brule/_names.py
brule-0.2.0.dist-info/LICENSE
brule-0.2.0.dist-info/METADATA
brule-0.2.0.dist-info/WHEEL
brule-0.2.0.dist-info/top_level.txt
brule-0.2.0.dist-info/RECORD
