Metadata-Version: 2.1
Name: brule
Version: 0.2.0
Summary: Dr. Steve Brule name generator
Home-page: https://github.com/dbusteed/brule
Author: Davis Busteed
Author-email: busteed.davis@gmail.com
License: MIT
Platform: UNKNOWN
Classifier: License :: OSI Approved :: MIT License
Classifier: Programming Language :: Python :: 3
Classifier: Programming Language :: Python :: 3.8
